sapcloudsdk/__init__.py
sapcloudsdk/__main__.py
sapcloudsdk/arguments.py
sapcloudsdk/github.py
sapcloudsdk/run.py
sapcloudsdk/sdk.py
sapcloudsdk-0.1.0.dist-info/entry_points.txt
sapcloudsdk-0.1.0.dist-info/WHEEL
sapcloudsdk-0.1.0.dist-info/METADATA
sapcloudsdk-0.1.0.dist-info/RECORD
