Metadata-Version: 2.1
Name: sapcloudsdk
Version: 0.1.0
Summary: 
Author: Florian Richter
Author-email: florian.richter@sap.com
Requires-Python: >=3.10,<4.0
Classifier: Programming Language :: Python :: 3
Classifier: Programming Language :: Python :: 3.10
Requires-Dist: Markdown (>=3.3.7,<4.0.0)
Requires-Dist: requests (>=2.27.1,<3.0.0)
